Metadata-Version: 1.0
Name: add-swap
Version: 1.0
Summary: Add numbers and swap them
Home-page: http://github.com
Author: Sanchay
Author-email: sanchay.pahalwani@gmail.com
License: MIT
Platform: UNKNOWN
